async_service/__init__.py
async_service/_utils.py
async_service/abc.py
async_service/asyncio.py
async_service/asyncio_compat.py
async_service/base.py
async_service/exceptions.py
async_service/py.typed
async_service/stats.py
async_service/trio.py
async_service/typing.py
async_service/tools/__init__.py
async_service/tools/_dag_test.py
async_service-0.1.0a11.dist-info/LICENSE
async_service-0.1.0a11.dist-info/METADATA
async_service-0.1.0a11.dist-info/WHEEL
async_service-0.1.0a11.dist-info/top_level.txt
async_service-0.1.0a11.dist-info/RECORD
