Metadata-Version: 2.1
Name: async-service
Version: 0.1.0a11
Summary: async-service: Lifecycle management for async applications
Home-page: https://github.com/ethereum/async-service
Author: The Ethereum Foundation
Author-email: snakecharmers@ethereum.org
License: MIT
Keywords: ethereum
Platform: UNKNOWN
Classifier: Development Status :: 3 - Alpha
Classifier: Intended Audience :: Developers
Classifier: License :: OSI Approved :: MIT License
Classifier: Natural Language :: English
Classifier: Programming Language :: Python :: 3
Classifier: Programming Language :: Python :: 3.6
Classifier: Programming Language :: Python :: 3.7
Classifier: Programming Language :: Python :: 3.8
Classifier: Programming Language :: Python :: Implementation :: PyPy
Requires-Python: >=3.6, <4
Requires-Dist: async-generator (<2,>=1.10)
Requires-Dist: trio-typing (<0.6,>=0.5)
Requires-Dist: trio (<0.17,>=0.16)
Provides-Extra: dev
Requires-Dist: Sphinx (<2,>=1.6.5) ; extra == 'dev'
Requires-Dist: black (==19.3b) ; extra == 'dev'
Requires-Dist: bumpversion (<1,>=0.5.3) ; extra == 'dev'
Requires-Dist: flake8 (==3.7.9) ; extra == 'dev'
Requires-Dist: hypothesis (==4.44.4) ; extra == 'dev'
Requires-Dist: ipython ; extra == 'dev'
Requires-Dist: isort (<5,>=4.2.15) ; extra == 'dev'
Requires-Dist: mypy (==0.782) ; extra == 'dev'
Requires-Dist: pydocstyle (<4,>=3.0.0) ; extra == 'dev'
Requires-Dist: pytest-watch (<5,>=4.1.0) ; extra == 'dev'
Requires-Dist: pytest-xdist ; extra == 'dev'
Requires-Dist: pytest (==5.4.1) ; extra == 'dev'
Requires-Dist: sphinx-rtd-theme (>=0.1.9) ; extra == 'dev'
Requires-Dist: towncrier (<20,>=19.2.0) ; extra == 'dev'
Requires-Dist: tox (==3.14.6) ; extra == 'dev'
Requires-Dist: twine ; extra == 'dev'
Requires-Dist: wheel ; extra == 'dev'
Provides-Extra: doc
Requires-Dist: Sphinx (<2,>=1.6.5) ; extra == 'doc'
Requires-Dist: sphinx-rtd-theme (>=0.1.9) ; extra == 'doc'
Requires-Dist: towncrier (<20,>=19.2.0) ; extra == 'doc'
Provides-Extra: lint
Requires-Dist: black (==19.3b) ; extra == 'lint'
Requires-Dist: flake8 (==3.7.9) ; extra == 'lint'
Requires-Dist: isort (<5,>=4.2.15) ; extra == 'lint'
Requires-Dist: mypy (==0.782) ; extra == 'lint'
Requires-Dist: pydocstyle (<4,>=3.0.0) ; extra == 'lint'
Provides-Extra: test
Requires-Dist: hypothesis (==4.44.4) ; extra == 'test'
Requires-Dist: pytest-xdist ; extra == 'test'
Requires-Dist: pytest (==5.4.1) ; extra == 'test'
Requires-Dist: tox (==3.14.6) ; extra == 'test'
Provides-Extra: test-asyncio
Requires-Dist: pytest-asyncio (<0.11,>=0.10.0) ; extra == 'test-asyncio'
Provides-Extra: test-trio
Requires-Dist: pytest-trio (<0.7.0,>=0.6.0) ; extra == 'test-trio'
